cuesubmit/Config.py
cuesubmit/Constants.py
cuesubmit/JobTypes.py
cuesubmit/Layer.py
cuesubmit/Submission.py
cuesubmit/Util.py
cuesubmit/Validators.py
cuesubmit/__init__.py
cuesubmit/__main__.py
cuesubmit/images/OpenCue.png
cuesubmit/ui/Command.py
cuesubmit/ui/Frame.py
cuesubmit/ui/Job.py
cuesubmit/ui/SettingsWidgets.py
cuesubmit/ui/Style.py
cuesubmit/ui/Submit.py
cuesubmit/ui/Widgets.py
cuesubmit/ui/__init__.py
opencue_cuesubmit-1.13.8.dist-info/METADATA
opencue_cuesubmit-1.13.8.dist-info/WHEEL
opencue_cuesubmit-1.13.8.dist-info/entry_points.txt
opencue_cuesubmit-1.13.8.dist-info/RECORD
